primerdriver/__init__.py
primerdriver/__main__.py
primerdriver/checks.py
primerdriver/config.py
primerdriver/exceptions.py
primerdriver/expression_sys_loader.py
primerdriver/expression_systems/Aplysia californica.json
primerdriver/expression_systems/Arabidopsis thaliana.json
primerdriver/expression_systems/Arbacia punctulata.json
primerdriver/expression_systems/Ashbya gossypii ATCC 10895.json
primerdriver/expression_systems/Bacillus subtilis.json
primerdriver/expression_systems/Bombina bombina.json
primerdriver/expression_systems/Brachypodium distachyon.json
primerdriver/expression_systems/Branchiostoma floridae.json
primerdriver/expression_systems/Caenorhabditis elegans.json
primerdriver/expression_systems/Callosobruchus maculatus.json
primerdriver/expression_systems/Canis familiaris.json
primerdriver/expression_systems/Canis lupus.json
primerdriver/expression_systems/Carassius auratus.json
primerdriver/expression_systems/Catla catla.json
primerdriver/expression_systems/Catostomus commersonii.json
primerdriver/expression_systems/Caulobacter crescentus.json
primerdriver/expression_systems/Cavia porcellus.json
"primerdriver/expression_systems/Chlamydomonas reinhardtii,.json"
primerdriver/expression_systems/Chorthippus parallelus.json
primerdriver/expression_systems/Ciona intestinalis.json
primerdriver/expression_systems/Clarias gariepinus.json
primerdriver/expression_systems/Cricetus cricetus.json
primerdriver/expression_systems/Cyprinodon variegatus.json
primerdriver/expression_systems/Danio rerio.json
primerdriver/expression_systems/Daphnia pulex.json
primerdriver/expression_systems/Dictyostelium discoideum.json
primerdriver/expression_systems/Drosophila melanogaster.json
primerdriver/expression_systems/Emiliania huxleyi.json
primerdriver/expression_systems/Eschirichia coli K12.json
primerdriver/expression_systems/Euprymna scolopes.json
primerdriver/expression_systems/Felis catus.json
primerdriver/expression_systems/Gallus gallus.json
primerdriver-1.6.0.dist-info/LICENSE
primerdriver-1.6.0.dist-info/METADATA
primerdriver-1.6.0.dist-info/WHEEL
primerdriver-1.6.0.dist-info/RECORD
