Metadata-Version: 2.1
Name: primerdriver
Version: 1.6.0
Summary: Automated design of mutagenic PCR primers
Home-page: https://github.com/kvdomingo/primerdriver
Author: Kenneth V. Domingo
Author-email: hello@kvd.studio
Requires-Python: >=3.9,<3.11
Classifier: Development Status :: 5 - Production/Stable
Classifier: Framework :: Flask
Classifier: Intended Audience :: Science/Research
Classifier: License :: OSI Approved :: GNU General Public License v3 (GPLv3)
Classifier: Programming Language :: Python :: 3
Classifier: Programming Language :: Python :: 3.9
Classifier: Programming Language :: Python :: 3.10
Classifier: Typing :: Typed
Requires-Dist: Flask (>=2.1.2,<3.0.0)
Requires-Dist: Flask-Caching (>=1.10.1,<2.0.0)
Requires-Dist: biopython (==1.76)
Requires-Dist: furo (>=2023.3.27,<2024.0.0)
Requires-Dist: gunicorn[gthread] (>=20.1.0,<21.0.0)
Requires-Dist: loguru (>=0.6.0,<0.7.0)
Requires-Dist: numpy (==1.24.4)
Requires-Dist: pandas (==1.4.2)
Requires-Dist: pydantic (<2.0.0)
Requires-Dist: python-dotenv (>=1.0.0,<2.0.0)
Requires-Dist: requests (>=2.27.1,<3.0.0)
Requires-Dist: tabulate (>=0.8.9,<0.9.0)
